llmvm/client/__main__.py
llmvm/client/awesome_prompts.csv
llmvm/client/cli.py
llmvm/client/client.py
llmvm/client/custom_completer.py
llmvm/client/markdown_renderer.py
llmvm/client/parsing.py
llmvm/client/printing.py
llmvm/common/__init__.py
llmvm/common/anthropic_executor.py
llmvm/common/bedrock_executor.py
llmvm/common/bedrock_helpers.py
llmvm/common/container.py
llmvm/common/deepseek_executor.py
llmvm/common/deepseek_tokenizer/tokenizer.json
llmvm/common/deepseek_tokenizer/tokenizer_config.json
llmvm/common/gemini_executor.py
llmvm/common/helpers.py
llmvm/common/logging_helpers.py
llmvm/common/object_transformers.py
llmvm/common/objects.py
llmvm/common/openai_executor.py
llmvm/common/openai_tool_translator.py
llmvm/common/pdf.py
llmvm/common/perf.py
llmvm/common/singleton.py
llmvm/config.yaml
llmvm/model_prices_and_context_window.json
llmvm/server/__init__.py
llmvm/server/__main__.py
llmvm/server/auto_global_dict.py
llmvm/server/base_library/content_downloader.py
llmvm/server/base_library/function_bindable.py
llmvm/server/base_library/searcher.py
llmvm/server/base_library/source.py
llmvm/server/bcl.py
llmvm/server/mcp_monitor.py
llmvm/server/persistent_cache.py
llmvm/server/prompts/python/__init__.py
llmvm/server/prompts/python/answer.prompt
llmvm/server/prompts/python/answer_error_correction.prompt
llmvm/server/prompts/python/answer_nocontext.prompt
llmvm/server/prompts/python/answer_primitive.prompt
llmvm/server/prompts/python/answer_regen_code_or_rewrite.prompt
llmvm/server/prompts/python/assistant_result.prompt
llmvm/server/prompts/python/coerce.prompt
llmvm/server/prompts/python/document_chunk.prompt
llmvm/server/prompts/python/download_and_validate.prompt
llmvm/server/prompts/python/foreach_result.prompt
llmvm/server/prompts/python/function_call_result.prompt
llmvm/server/prompts/python/functionmeta_result.prompt
llmvm/server/prompts/python/list_result.prompt
llmvm/server/prompts/python/llm_bind_global.prompt
llmvm/server/prompts/python/llm_call.prompt
llmvm_cli-1.5.5.dist-info/LICENSE
llmvm_cli-1.5.5.dist-info/METADATA
llmvm_cli-1.5.5.dist-info/WHEEL
llmvm_cli-1.5.5.dist-info/RECORD
