Metadata-Version: 2.3
Name: llmvm-cli
Version: 1.5.5
Summary: Command Line LLM with client-side tools support.
Author: 9600 devs
Author-email: contact@9600.dev
Requires-Python: >=3.11,<4.0
Classifier: Programming Language :: Python :: 3
Classifier: Programming Language :: Python :: 3.11
Classifier: Programming Language :: Python :: 3.12
Classifier: Programming Language :: Python :: 3.13
Requires-Dist: aiofiles (>=23.2.1,<24.0.0)
Requires-Dist: aiohttp (>=3.11.13,<4.0.0)
Requires-Dist: aiosignal (>=1.3.1,<2.0.0)
Requires-Dist: annotated-types (>=0.7.0,<0.8.0)
Requires-Dist: anthropic (>=0.60.0,<0.61.0)
Requires-Dist: anyio (>=4.4.0,<5.0.0)
Requires-Dist: astunparse (>=1.6.3,<2.0.0)
Requires-Dist: async-timeout (>=4.0.3,<5.0.0)
Requires-Dist: attrs (>=23.2.0,<24.0.0)
Requires-Dist: beautifulsoup4 (>=4.12.3,<5.0.0)
Requires-Dist: boto3 (>=1.37.28,<2.0.0)
Requires-Dist: botocore (>=1.37.28,<2.0.0)
Requires-Dist: bs4 (>=0.0.2,<0.0.3)
Requires-Dist: cachetools (>=5.3.3,<6.0.0)
Requires-Dist: certifi (>=2024.6.2,<2025.0.0)
Requires-Dist: cffi (>=1.16.0,<2.0.0)
Requires-Dist: charset-normalizer (>=3.3.2,<4.0.0)
Requires-Dist: click (>=8.1.8,<9.0.0)
Requires-Dist: click-default-group (>=1.2.4,<2.0.0)
Requires-Dist: colorama (>=0.4.6,<0.5.0)
Requires-Dist: cryptography (>=44.0.2,<45.0.0)
Requires-Dist: dataclasses-json (>=0.6.7,<0.7.0)
Requires-Dist: dateparser (>=1.2.0,<2.0.0)
Requires-Dist: dill (>=0.3.8,<0.4.0)
Requires-Dist: distro (>=1.9.0,<2.0.0)
Requires-Dist: docstring-parser (>=0.16,<0.17)
Requires-Dist: exceptiongroup (>=1.2.1,<2.0.0)
Requires-Dist: fastapi (>=0.116.1,<0.117.0)
Requires-Dist: filelock (>=3.14.0,<4.0.0)
Requires-Dist: frozendict (>=2.4.4,<3.0.0)
Requires-Dist: frozenlist (>=1.4.1,<2.0.0)
Requires-Dist: fsspec (>=2024.6.0,<2025.0.0)
Requires-Dist: googlesearch-python (>=1.3.0,<2.0.0)
Requires-Dist: greenlet (>=3.0.3,<4.0.0)
Requires-Dist: grpcio (>=1.64.1,<2.0.0)
Requires-Dist: gspread (>=6.1.3,<7.0.0)
Requires-Dist: gspread-dataframe (>=4.0.0,<5.0.0)
Requires-Dist: h11 (>=0.16.0,<0.17.0)
Requires-Dist: html5lib (>=1.1,<2.0)
Requires-Dist: httpcore (>=1.0.5,<2.0.0)
Requires-Dist: httpx (>=0.28.1,<0.29.0)
Requires-Dist: idna (>=3.7,<4.0)
Requires-Dist: jinja2 (>=3.1.4,<4.0.0)
Requires-Dist: joblib (>=1.4.2,<2.0.0)
Requires-Dist: jsonpatch (>=1.33,<2.0)
Requires-Dist: jsonpickle (>=3.2.1,<4.0.0)
Requires-Dist: jsonpointer (>=3.0.0,<4.0.0)
Requires-Dist: lxml (>=5.2.2,<6.0.0)
Requires-Dist: markdown-it-py (>=3.0.0,<4.0.0)
Requires-Dist: markdown2 (>=2.5.3,<3.0.0)
Requires-Dist: markdownify (>=0.12.1,<0.13.0)
Requires-Dist: markupsafe (>=2.1.5,<3.0.0)
Requires-Dist: marshmallow (>=3.21.3,<4.0.0)
Requires-Dist: matplotlib (>=3.9.0,<4.0.0)
Requires-Dist: mcp (>=1.9.4,<2.0.0)
Requires-Dist: mdurl (>=0.1.2,<0.2.0)
Requires-Dist: mpmath (>=1.3.0,<2.0.0)
Requires-Dist: multidict (>=6.0.5,<7.0.0)
Requires-Dist: multitasking (>=0.0.11,<0.0.12)
Requires-Dist: mypy-extensions (>=1.0.0,<2.0.0)
Requires-Dist: nest-asyncio (>=1.6.0,<2.0.0)
Requires-Dist: networkx (>=3.3,<4.0)
Requires-Dist: numpy (>=1.26.4,<2.0.0)
Requires-Dist: numpy-financial (>=1.0.0,<2.0.0)
Requires-Dist: openai (>=1.98.0,<2.0.0)
Requires-Dist: orjson (>=3.10.4,<4.0.0)
Requires-Dist: pandas (>=2.2.2,<3.0.0)
Requires-Dist: pdf2image (>=1.17.0,<2.0.0)
Requires-Dist: pdfminer-six (>=20231228,<20231229)
Requires-Dist: pdfplumber (>=0.11.1,<0.12.0)
Requires-Dist: peewee (>=3.17.5,<4.0.0)
Requires-Dist: pillow (>=10.3.0,<11.0.0)
Requires-Dist: platformdirs (>=4.2.2,<5.0.0)
Requires-Dist: playwright (>=1.50.0,<2.0.0)
Requires-Dist: prompt-toolkit (>=3.0.47,<4.0.0)
Requires-Dist: proto-plus (>=1.23.0,<2.0.0)
Requires-Dist: pyasn1 (>=0.6.0,<0.7.0)
Requires-Dist: pyasn1-modules (>=0.4.0,<0.5.0)
Requires-Dist: pycparser (>=2.22,<3.0)
Requires-Dist: pydantic (>=2.7.4,<3.0.0)
Requires-Dist: pyee (>=12.1.1,<13.0.0)
Requires-Dist: pygments (>=2.18.0,<3.0.0)
Requires-Dist: pypdf (>=4.2.0,<5.0.0)
Requires-Dist: pypdfium2 (>=4.30.0,<5.0.0)
Requires-Dist: pyperclip (>=1.8.2,<2.0.0)
Requires-Dist: pyte (>=0.8.2,<0.9.0)
Requires-Dist: pytesseract (>=0.3.10,<0.4.0)
Requires-Dist: python-dateutil (>=2.9.0.post0,<3.0.0)
Requires-Dist: python-multipart (>=0.0.20,<0.0.21)
Requires-Dist: pytz (>=2024.1,<2025.0)
Requires-Dist: pyyaml (>=6.0.1,<7.0.0)
Requires-Dist: regex (>=2024.5.15,<2025.0.0)
Requires-Dist: requests (>=2.32.3,<3.0.0)
Requires-Dist: rich (>=13.7.1,<14.0.0)
Requires-Dist: rsa (>=4.9,<5.0)
Requires-Dist: safetensors (>=0.4.3,<0.5.0)
Requires-Dist: scikit-learn (>=1.5.0,<2.0.0)
Requires-Dist: scipy (>=1.13.1,<2.0.0)
Requires-Dist: sec-api (>=1.0.18,<2.0.0)
Requires-Dist: serpapi (>=0.1.5,<0.2.0)
Requires-Dist: six (>=1.16.0,<2.0.0)
Requires-Dist: sniffio (>=1.3.1,<2.0.0)
Requires-Dist: soupsieve (>=2.5,<3.0)
Requires-Dist: sqlalchemy (>=2.0.30,<3.0.0)
Requires-Dist: starlette (>=0.47.2,<0.48.0)
Requires-Dist: sympy (>=1.12.1,<2.0.0)
Requires-Dist: tenacity (>=8.3.0,<9.0.0)
Requires-Dist: threadpoolctl (>=3.5.0,<4.0.0)
Requires-Dist: tiktoken (>=0.9.0,<0.10.0)
Requires-Dist: tokenizers (>=0.21.0,<0.22.0)
Requires-Dist: tqdm (>=4.66.4,<5.0.0)
Requires-Dist: transformers (>=4.51.3,<5.0.0)
Requires-Dist: typing-extensions (>=4.12.2,<5.0.0)
Requires-Dist: typing-inspect (>=0.9.0,<0.10.0)
Requires-Dist: tzdata (>=2024.1,<2025.0)
Requires-Dist: urllib3 (>=2.2.1,<3.0.0)
Requires-Dist: uvicorn (>=0.30.1,<0.31.0)
Requires-Dist: wcwidth (>=0.2.13,<0.3.0)
Requires-Dist: webencodings (>=0.5.1,<0.6.0)
Requires-Dist: wheel (>=0.43.0,<0.44.0)
Requires-Dist: yarl (>=1.9.4,<2.0.0)
Requires-Dist: yfinance (>=0.2.54,<0.3.0)
Project-URL: Homepage, https://github.com/9600dev/llmvm
Project-URL: Repository, https://github.com/9600dev/llmvm
